[
  {
    "name": "Thompson Lake via Granite Creek Trail",
    "dateHiked": "2022-06-11",
    "href": "https://www.wta.org/go-hiking/trip-reports/trip_report-2022-06-12-4765309267",
    "miles": "14.2",
    "elevation": "3,400"
  },
  {
    "name": "Skyline Trail Loop, Rampart Ridge Loop",
    "dateHiked": "2022-05-29",
    "href": "https://www.wta.org/go-hiking/trip-reports/trip_report-2022-06-12-5619961040",
    "miles": "9.2",
    "elevation": "1,100"
  },
  {
    "name": "Mount Si",
    "dateHiked": "2022-05-28",
    "href": "https://www.wta.org/go-hiking/trip-reports/trip_report-2022-06-12-8518405632",
    "miles": "8.0",
    "elevation": "3,150"
  },
  {
    "name": "Skyline Trail Loop",
    "dateHiked": "2021-10-16",
    "href": "https://www.wta.org/go-hiking/trip-reports/trip_report-2021-10-17-1652164162",
    "miles": "5.5",
    "elevation": "1,450"
  },
  {
    "name": "Rattlesnake Ledge",
    "dateHiked": "2021-09-25",
    "href": "https://www.wta.org/go-hiking/trip-reports/trip_report-2021-09-27-9614801592",
    "miles": "4.0",
    "elevation": "1,160"
  },
  {
    "name": "Greg Ball Trail to Wallace Lake",
    "dateHiked": "2022-06-26",
    "href": "https://www.wta.org/go-hiking/trip-reports/trip_report.2022-06-27.8716286302",
    "miles": "10.0",
    "elevation": "1,500"
  }
]
